semopy/__init__.py
semopy/example.py
semopy/full_model.py
semopy/inspector.py
semopy/model.py
semopy/model_abstract.py
semopy/model_nl.py
semopy/optimizer.py
semopy/parser.py
semopy/political_democracy.py
semopy/polycorr.py
semopy/regsem.py
semopy/stats.py
semopy/test_model.py
semopy/test_optimizer.py
semopy/test_parser.py
semopy/utils.py
semopy/visualization.py
semopy/model_generator/__init__.py
semopy/model_generator/datagenerator.py
semopy/model_generator/generator.py
semopy/model_generator/paramgenerator.py
semopy/model_generator/structgenerator.py
semopy/model_generator/utils.py
semopy-1.2.4.dist-info/LICENSE.md
semopy-1.2.4.dist-info/METADATA
semopy-1.2.4.dist-info/WHEEL
semopy-1.2.4.dist-info/top_level.txt
semopy-1.2.4.dist-info/RECORD
