Metadata-Version: 2.1
Name: semopy
Version: 1.2.4
Summary: Structural Equation Modeling optimization package.
Home-page: https://bitbucket.org/herrberg/semopy/
Author: Meshcheryakov A. Georgy
Author-email: metsheryakov_ga@spbstu.ru
License: UNKNOWN
Platform: UNKNOWN
Classifier: Programming Language :: Python :: 3
Classifier: License :: OSI Approved :: MIT License
Classifier: Operating System :: OS Independent
Requires-Dist: scipy
Requires-Dist: numpy
Requires-Dist: pandas
Requires-Dist: graphviz
Requires-Dist: Cython
Requires-Dist: portmin
